{
 "custom_fields": [
  {
   "_assign": null, 
   "_comments": null, 
   "_liked_by": null, 
   "_user_tags": null, 
   "allow_on_submit": 0, 
   "bold": 1, 
   "collapsible": 0, 
   "collapsible_depends_on": null, 
   "columns": 0, 
   "creation": "2019-07-15 12:29:06.806427", 
   "default": null, 
   "depends_on": null, 
   "description": null, 
   "docstatus": 0, 
   "dt": "Patient", 
   "fetch_from": null, 
   "fetch_if_empty": 0, 
   "fieldname": "country", 
   "fieldtype": "Data", 
   "hidden": 0, 
   "idx": 33, 
   "ignore_user_permissions": 0, 
   "ignore_xss_filter": 0, 
   "in_global_search": 0, 
   "in_list_view": 0, 
   "in_standard_filter": 0, 
   "insert_after": "state", 
   "label": "Country", 
   "modified": "2019-07-15 12:29:06.806427", 
   "modified_by": "Administrator", 
   "name": "Patient-country", 
   "no_copy": 0, 
   "options": null, 
   "owner": "Administrator", 
   "parent": null, 
   "parentfield": null, 
   "parenttype": null, 
   "permlevel": 0, 
   "precision": "", 
   "print_hide": 0, 
   "print_hide_if_no_value": 0, 
   "print_width": null, 
   "read_only": 0, 
   "report_hide": 0, 
   "reqd": 0, 
   "search_index": 0, 
   "translatable": 1, 
   "unique": 0, 
   "width": null
  }, 
  {
   "_assign": null, 
   "_comments": null, 
   "_liked_by": null, 
   "_user_tags": null, 
   "allow_on_submit": 0, 
   "bold": 1, 
   "collapsible": 0, 
   "collapsible_depends_on": null, 
   "columns": 0, 
   "creation": "2019-07-15 12:29:05.266761", 
   "default": null, 
   "depends_on": null, 
   "description": null, 
   "docstatus": 0, 
   "dt": "Patient", 
   "fetch_from": null, 
   "fetch_if_empty": 0, 
   "fieldname": "state", 
   "fieldtype": "Data", 
   "hidden": 0, 
   "idx": 32, 
   "ignore_user_permissions": 0, 
   "ignore_xss_filter": 0, 
   "in_global_search": 0, 
   "in_list_view": 0, 
   "in_standard_filter": 0, 
   "insert_after": "city", 
   "label": "State", 
   "modified": "2019-07-15 12:29:05.266761", 
   "modified_by": "Administrator", 
   "name": "Patient-state", 
   "no_copy": 0, 
   "options": null, 
   "owner": "Administrator", 
   "parent": null, 
   "parentfield": null, 
   "parenttype": null, 
   "permlevel": 0, 
   "precision": "", 
   "print_hide": 0, 
   "print_hide_if_no_value": 0, 
   "print_width": null, 
   "read_only": 0, 
   "report_hide": 0, 
   "reqd": 0, 
   "search_index": 0, 
   "translatable": 1, 
   "unique": 0, 
   "width": null
  }, 
  {
   "_assign": null, 
   "_comments": null, 
   "_liked_by": null, 
   "_user_tags": null, 
   "allow_on_submit": 0, 
   "bold": 1, 
   "collapsible": 0, 
   "collapsible_depends_on": null, 
   "columns": 0, 
   "creation": "2019-07-15 12:29:03.819381", 
   "default": null, 
   "depends_on": null, 
   "description": null, 
   "docstatus": 0, 
   "dt": "Patient", 
   "fetch_from": null, 
   "fetch_if_empty": 0, 
   "fieldname": "city", 
   "fieldtype": "Data", 
   "hidden": 0, 
   "idx": 31, 
   "ignore_user_permissions": 0, 
   "ignore_xss_filter": 0, 
   "in_global_search": 0, 
   "in_list_view": 0, 
   "in_standard_filter": 0, 
   "insert_after": "column_break_27", 
   "label": "City", 
   "modified": "2019-07-15 12:29:03.819381", 
   "modified_by": "Administrator", 
   "name": "Patient-city", 
   "no_copy": 0, 
   "options": null, 
   "owner": "Administrator", 
   "parent": null, 
   "parentfield": null, 
   "parenttype": null, 
   "permlevel": 0, 
   "precision": "", 
   "print_hide": 0, 
   "print_hide_if_no_value": 0, 
   "print_width": null, 
   "read_only": 0, 
   "report_hide": 0, 
   "reqd": 0, 
   "search_index": 0, 
   "translatable": 1, 
   "unique": 0, 
   "width": null
  }, 
  {
   "_assign": null, 
   "_comments": null, 
   "_liked_by": null, 
   "_user_tags": null, 
   "allow_on_submit": 0, 
   "bold": 1, 
   "collapsible": 0, 
   "collapsible_depends_on": null, 
   "columns": 0, 
   "creation": "2019-07-15 12:29:03.276050", 
   "default": null, 
   "depends_on": null, 
   "description": null, 
   "docstatus": 0, 
   "dt": "Patient", 
   "fetch_from": null, 
   "fetch_if_empty": 0, 
   "fieldname": "column_break_27", 
   "fieldtype": "Column Break", 
   "hidden": 0, 
   "idx": 30, 
   "ignore_user_permissions": 0, 
   "ignore_xss_filter": 0, 
   "in_global_search": 0, 
   "in_list_view": 0, 
   "in_standard_filter": 0, 
   "insert_after": "zip_code", 
   "label": null, 
   "modified": "2019-07-15 12:29:03.276050", 
   "modified_by": "Administrator", 
   "name": "Patient-column_break_27", 
   "no_copy": 0, 
   "options": null, 
   "owner": "Administrator", 
   "parent": null, 
   "parentfield": null, 
   "parenttype": null, 
   "permlevel": 0, 
   "precision": "", 
   "print_hide": 0, 
   "print_hide_if_no_value": 0, 
   "print_width": null, 
   "read_only": 0, 
   "report_hide": 0, 
   "reqd": 0, 
   "search_index": 0, 
   "translatable": 0, 
   "unique": 0, 
   "width": null
  }, 
  {
   "_assign": null, 
   "_comments": null, 
   "_liked_by": null, 
   "_user_tags": null, 
   "allow_on_submit": 0, 
   "bold": 1, 
   "collapsible": 0, 
   "collapsible_depends_on": null, 
   "columns": 0, 
   "creation": "2019-07-15 12:29:01.780445", 
   "default": null, 
   "depends_on": null, 
   "description": null, 
   "docstatus": 0, 
   "dt": "Patient", 
   "fetch_from": null, 
   "fetch_if_empty": 0, 
   "fieldname": "zip_code", 
   "fieldtype": "Data", 
   "hidden": 0, 
   "idx": 29, 
   "ignore_user_permissions": 0, 
   "ignore_xss_filter": 0, 
   "in_global_search": 0, 
   "in_list_view": 0, 
   "in_standard_filter": 0, 
   "insert_after": "address_line2", 
   "label": "Zip Code", 
   "modified": "2019-07-15 12:29:01.780445", 
   "modified_by": "Administrator", 
   "name": "Patient-zip_code", 
   "no_copy": 0, 
   "options": null, 
   "owner": "Administrator", 
   "parent": null, 
   "parentfield": null, 
   "parenttype": null, 
   "permlevel": 0, 
   "precision": "", 
   "print_hide": 0, 
   "print_hide_if_no_value": 0, 
   "print_width": null, 
   "read_only": 0, 
   "report_hide": 0, 
   "reqd": 0, 
   "search_index": 0, 
   "translatable": 1, 
   "unique": 0, 
   "width": null
  }, 
  {
   "_assign": null, 
   "_comments": null, 
   "_liked_by": null, 
   "_user_tags": null, 
   "allow_on_submit": 0, 
   "bold": 1, 
   "collapsible": 0, 
   "collapsible_depends_on": null, 
   "columns": 0, 
   "creation": "2019-07-15 12:28:59.279311", 
   "default": null, 
   "depends_on": null, 
   "description": null, 
   "docstatus": 0, 
   "dt": "Patient", 
   "fetch_from": null, 
   "fetch_if_empty": 0, 
   "fieldname": "address_line2", 
   "fieldtype": "Data", 
   "hidden": 0, 
   "idx": 28, 
   "ignore_user_permissions": 0, 
   "ignore_xss_filter": 0, 
   "in_global_search": 0, 
   "in_list_view": 0, 
   "in_standard_filter": 0, 
   "insert_after": "address_line1", 
   "label": "Address Line2", 
   "modified": "2019-07-15 12:28:59.279311", 
   "modified_by": "Administrator", 
   "name": "Patient-address_line2", 
   "no_copy": 0, 
   "options": null, 
   "owner": "Administrator", 
   "parent": null, 
   "parentfield": null, 
   "parenttype": null, 
   "permlevel": 0, 
   "precision": "", 
   "print_hide": 0, 
   "print_hide_if_no_value": 0, 
   "print_width": null, 
   "read_only": 0, 
   "report_hide": 0, 
   "reqd": 0, 
   "search_index": 0, 
   "translatable": 1, 
   "unique": 0, 
   "width": null
  }, 
  {
   "_assign": null, 
   "_comments": null, 
   "_liked_by": null, 
   "_user_tags": null, 
   "allow_on_submit": 0, 
   "bold": 1, 
   "collapsible": 0, 
   "collapsible_depends_on": null, 
   "columns": 0, 
   "creation": "2019-07-15 12:28:57.246749", 
   "default": null, 
   "depends_on": null, 
   "description": null, 
   "docstatus": 0, 
   "dt": "Patient", 
   "fetch_from": null, 
   "fetch_if_empty": 0, 
   "fieldname": "address_line1", 
   "fieldtype": "Data", 
   "hidden": 0, 
   "idx": 27, 
   "ignore_user_permissions": 0, 
   "ignore_xss_filter": 0, 
   "in_global_search": 0, 
   "in_list_view": 0, 
   "in_standard_filter": 0, 
   "insert_after": "address_detail", 
   "label": "Address Line 1", 
   "modified": "2019-07-15 12:28:57.246749", 
   "modified_by": "Administrator", 
   "name": "Patient-address_line1", 
   "no_copy": 0, 
   "options": null, 
   "owner": "Administrator", 
   "parent": null, 
   "parentfield": null, 
   "parenttype": null, 
   "permlevel": 0, 
   "precision": "", 
   "print_hide": 0, 
   "print_hide_if_no_value": 0, 
   "print_width": null, 
   "read_only": 0, 
   "report_hide": 0, 
   "reqd": 0, 
   "search_index": 0, 
   "translatable": 1, 
   "unique": 0, 
   "width": null
  }, 
  {
   "_assign": null, 
   "_comments": null, 
   "_liked_by": null, 
   "_user_tags": null, 
   "allow_on_submit": 0, 
   "bold": 1, 
   "collapsible": 1, 
   "collapsible_depends_on": null, 
   "columns": 0, 
   "creation": "2019-07-15 12:28:56.352995", 
   "default": null, 
   "depends_on": null, 
   "description": null, 
   "docstatus": 0, 
   "dt": "Patient", 
   "fetch_from": null, 
   "fetch_if_empty": 0, 
   "fieldname": "address_detail", 
   "fieldtype": "Section Break", 
   "hidden": 0, 
   "idx": 26, 
   "ignore_user_permissions": 0, 
   "ignore_xss_filter": 0, 
   "in_global_search": 0, 
   "in_list_view": 0, 
   "in_standard_filter": 0, 
   "insert_after": "patient_relation", 
   "label": "Address Detail", 
   "modified": "2019-07-15 12:28:56.352995", 
   "modified_by": "Administrator", 
   "name": "Patient-address_detail", 
   "no_copy": 0, 
   "options": null, 
   "owner": "Administrator", 
   "parent": null, 
   "parentfield": null, 
   "parenttype": null, 
   "permlevel": 0, 
   "precision": "", 
   "print_hide": 0, 
   "print_hide_if_no_value": 0, 
   "print_width": null, 
   "read_only": 0, 
   "report_hide": 0, 
   "reqd": 0, 
   "search_index": 0, 
   "translatable": 0, 
   "unique": 0, 
   "width": null
  }, 
  {
   "_assign": null, 
   "_comments": null, 
   "_liked_by": null, 
   "_user_tags": null, 
   "allow_on_submit": 0, 
   "bold": 0, 
   "collapsible": 0, 
   "collapsible_depends_on": null, 
   "columns": 0, 
   "creation": "2019-06-12 10:15:01.568552", 
   "default": null, 
   "depends_on": null, 
   "description": null, 
   "docstatus": 0, 
   "dt": "Patient", 
   "fetch_from": null, 
   "fetch_if_empty": 0, 
   "fieldname": "referrer_phone_no", 
   "fieldtype": "Data", 
   "hidden": 0, 
   "idx": 22, 
   "ignore_user_permissions": 0, 
   "ignore_xss_filter": 0, 
   "in_global_search": 0, 
   "in_list_view": 0, 
   "in_standard_filter": 0, 
   "insert_after": "referrer_name", 
   "label": "Referrer Phone No", 
   "modified": "2019-06-12 10:15:01.568552", 
   "modified_by": "Administrator", 
   "name": "Patient-referrer_phone_no", 
   "no_copy": 0, 
   "options": null, 
   "owner": "Administrator", 
   "parent": null, 
   "parentfield": null, 
   "parenttype": null, 
   "permlevel": 0, 
   "precision": "", 
   "print_hide": 0, 
   "print_hide_if_no_value": 0, 
   "print_width": null, 
   "read_only": 0, 
   "report_hide": 0, 
   "reqd": 0, 
   "search_index": 0, 
   "translatable": 1, 
   "unique": 0, 
   "width": null
  }, 
  {
   "_assign": null, 
   "_comments": null, 
   "_liked_by": null, 
   "_user_tags": null, 
   "allow_on_submit": 0, 
   "bold": 0, 
   "collapsible": 0, 
   "collapsible_depends_on": null, 
   "columns": 0, 
   "creation": "2019-06-12 10:15:00.947530", 
   "default": null, 
   "depends_on": null, 
   "description": null, 
   "docstatus": 0, 
   "dt": "Patient", 
   "fetch_from": null, 
   "fetch_if_empty": 0, 
   "fieldname": "referrer_name", 
   "fieldtype": "Data", 
   "hidden": 0, 
   "idx": 21, 
   "ignore_user_permissions": 0, 
   "ignore_xss_filter": 0, 
   "in_global_search": 0, 
   "in_list_view": 0, 
   "in_standard_filter": 0, 
   "insert_after": "phone", 
   "label": "Referrer Name", 
   "modified": "2019-06-12 10:15:00.947530", 
   "modified_by": "Administrator", 
   "name": "Patient-referrer_name", 
   "no_copy": 0, 
   "options": null, 
   "owner": "Administrator", 
   "parent": null, 
   "parentfield": null, 
   "parenttype": null, 
   "permlevel": 0, 
   "precision": "", 
   "print_hide": 0, 
   "print_hide_if_no_value": 0, 
   "print_width": null, 
   "read_only": 0, 
   "report_hide": 0, 
   "reqd": 0, 
   "search_index": 0, 
   "translatable": 1, 
   "unique": 0, 
   "width": null
  }, 
  {
   "_assign": null, 
   "_comments": null, 
   "_liked_by": null, 
   "_user_tags": null, 
   "allow_on_submit": 0, 
   "bold": 0, 
   "collapsible": 0, 
   "collapsible_depends_on": null, 
   "columns": 0, 
   "creation": "2019-06-11 15:25:44.429079", 
   "default": null, 
   "depends_on": null, 
   "description": null, 
   "docstatus": 0, 
   "dt": "Patient", 
   "fetch_from": null, 
   "fetch_if_empty": 0, 
   "fieldname": "family_name", 
   "fieldtype": "Link", 
   "hidden": 0, 
   "idx": 13, 
   "ignore_user_permissions": 0, 
   "ignore_xss_filter": 0, 
   "in_global_search": 0, 
   "in_list_view": 0, 
   "in_standard_filter": 0, 
   "insert_after": "name", 
   "label": "Family Name", 
   "modified": "2019-06-01 11:12:46.009241", 
   "modified_by": "Administrator", 
   "name": "Patient-family_name", 
   "no_copy": 0, 
   "options": "Family", 
   "owner": "Administrator", 
   "parent": null, 
   "parentfield": null, 
   "parenttype": null, 
   "permlevel": 0, 
   "precision": "", 
   "print_hide": 0, 
   "print_hide_if_no_value": 0, 
   "print_width": null, 
   "read_only": 0, 
   "report_hide": 0, 
   "reqd": 0, 
   "search_index": 0, 
   "translatable": 0, 
   "unique": 0, 
   "width": null
  }, 
  {
   "_assign": null, 
   "_comments": null, 
   "_liked_by": null, 
   "_user_tags": null, 
   "allow_on_submit": 0, 
   "bold": 0, 
   "collapsible": 0, 
   "collapsible_depends_on": null, 
   "columns": 0, 
   "creation": "2019-06-11 15:25:41.052592", 
   "default": null, 
   "depends_on": null, 
   "description": null, 
   "docstatus": 0, 
   "dt": "Patient", 
   "fetch_from": null, 
   "fetch_if_empty": 0, 
   "fieldname": "regular", 
   "fieldtype": "Check", 
   "hidden": 1, 
   "idx": 15, 
   "ignore_user_permissions": 0, 
   "ignore_xss_filter": 0, 
   "in_global_search": 0, 
   "in_list_view": 0, 
   "in_standard_filter": 0, 
   "insert_after": "column_break_14", 
   "label": "Regular", 
   "modified": "2019-05-16 00:27:52.404385", 
   "modified_by": "Administrator", 
   "name": "Patient-regular", 
   "no_copy": 0, 
   "options": null, 
   "owner": "Administrator", 
   "parent": null, 
   "parentfield": null, 
   "parenttype": null, 
   "permlevel": 0, 
   "precision": "", 
   "print_hide": 0, 
   "print_hide_if_no_value": 0, 
   "print_width": null, 
   "read_only": 0, 
   "report_hide": 0, 
   "reqd": 0, 
   "search_index": 0, 
   "translatable": 0, 
   "unique": 0, 
   "width": null
  }, 
  {
   "_assign": null, 
   "_comments": null, 
   "_liked_by": null, 
   "_user_tags": null, 
   "allow_on_submit": 0, 
   "bold": 0, 
   "collapsible": 0, 
   "collapsible_depends_on": null, 
   "columns": 0, 
   "creation": "2019-06-11 15:25:39.270512", 
   "default": null, 
   "depends_on": null, 
   "description": null, 
   "docstatus": 0, 
   "dt": "Patient", 
   "fetch_from": null, 
   "fetch_if_empty": 0, 
   "fieldname": "name", 
   "fieldtype": "Data", 
   "hidden": 1, 
   "idx": 12, 
   "ignore_user_permissions": 0, 
   "ignore_xss_filter": 0, 
   "in_global_search": 0, 
   "in_list_view": 0, 
   "in_standard_filter": 0, 
   "insert_after": "image", 
   "label": "Name", 
   "modified": "2019-05-16 00:27:51.532427", 
   "modified_by": "Administrator", 
   "name": "Patient-name", 
   "no_copy": 0, 
   "options": null, 
   "owner": "Administrator", 
   "parent": null, 
   "parentfield": null, 
   "parenttype": null, 
   "permlevel": 0, 
   "precision": "", 
   "print_hide": 0, 
   "print_hide_if_no_value": 0, 
   "print_width": null, 
   "read_only": 0, 
   "report_hide": 0, 
   "reqd": 0, 
   "search_index": 0, 
   "translatable": 1, 
   "unique": 0, 
   "width": null
  }
 ], 
 "custom_perms": [], 
 "doctype": "Patient", 
 "property_setters": [
  {
   "_assign": null, 
   "_comments": null, 
   "_liked_by": null, 
   "_user_tags": null, 
   "creation": "2019-07-15 12:41:24.438156", 
   "default_value": null, 
   "doc_type": "Patient", 
   "docstatus": 0, 
   "doctype_or_field": "DocType", 
   "field_name": null, 
   "idx": 0, 
   "modified": "2019-07-15 12:41:24.438156", 
   "modified_by": "Administrator", 
   "name": "Patient-read_only_onload", 
   "owner": "Administrator", 
   "parent": null, 
   "parentfield": null, 
   "parenttype": null, 
   "property": "read_only_onload", 
   "property_type": "Check", 
   "value": null
  }, 
  {
   "_assign": null, 
   "_comments": null, 
   "_liked_by": null, 
   "_user_tags": null, 
   "creation": "2019-07-15 02:44:55.032334", 
   "default_value": null, 
   "doc_type": "Patient", 
   "docstatus": 0, 
   "doctype_or_field": "DocField", 
   "field_name": "phone", 
   "idx": 0, 
   "modified": "2019-07-15 02:44:55.032334", 
   "modified_by": "Administrator", 
   "name": "Patient-phone-label", 
   "owner": "Administrator", 
   "parent": null, 
   "parentfield": null, 
   "parenttype": null, 
   "property": "label", 
   "property_type": "Data", 
   "value": "Alternate Mobile"
  }, 
  {
   "_assign": null, 
   "_comments": null, 
   "_liked_by": null, 
   "_user_tags": null, 
   "creation": "2019-06-11 17:14:02.430219", 
   "default_value": null, 
   "doc_type": "Patient", 
   "docstatus": 0, 
   "doctype_or_field": "DocField", 
   "field_name": "blood_group", 
   "idx": 0, 
   "modified": "2019-06-11 17:14:02.430219", 
   "modified_by": "Administrator", 
   "name": "Patient-blood_group-label", 
   "owner": "Administrator", 
   "parent": null, 
   "parentfield": null, 
   "parenttype": null, 
   "property": "idx", 
   "property_type": "Int", 
   "value": "1"
  }, 
  {
   "_assign": null, 
   "_comments": null, 
   "_liked_by": null, 
   "_user_tags": null, 
   "creation": "2019-06-11 12:57:19.191169", 
   "default_value": null, 
   "doc_type": "Patient", 
   "docstatus": 0, 
   "doctype_or_field": "DocField", 
   "field_name": "blood_group", 
   "idx": 0, 
   "modified": "2019-06-11 12:57:19.191169", 
   "modified_by": "Administrator", 
   "name": "Patient-blood_group-options", 
   "owner": "Administrator", 
   "parent": null, 
   "parentfield": null, 
   "parenttype": null, 
   "property": "options", 
   "property_type": "Text", 
   "value": "\nA Positive\nA Negative\nAB Positive\nAB Negative\nB Positive\nB Negative\nO Positive\nO Negative\nBombay"
  }, 
  {
   "_assign": null, 
   "_comments": null, 
   "_liked_by": null, 
   "_user_tags": null, 
   "creation": "2019-06-11 12:56:40.490420", 
   "default_value": null, 
   "doc_type": "Patient", 
   "docstatus": 0, 
   "doctype_or_field": "DocField", 
   "field_name": "report_preference", 
   "idx": 0, 
   "modified": "2019-06-11 12:56:40.490420", 
   "modified_by": "Administrator", 
   "name": "Patient-report_preference-default", 
   "owner": "Administrator", 
   "parent": null, 
   "parentfield": null, 
   "parenttype": null, 
   "property": "default", 
   "property_type": "Text", 
   "value": "Email"
  }, 
  {
   "_assign": null, 
   "_comments": null, 
   "_liked_by": null, 
   "_user_tags": null, 
   "creation": "2019-06-11 12:56:40.480727", 
   "default_value": null, 
   "doc_type": "Patient", 
   "docstatus": 0, 
   "doctype_or_field": "DocField", 
   "field_name": "customer", 
   "idx": 0, 
   "modified": "2019-06-11 12:56:40.480727", 
   "modified_by": "Administrator", 
   "name": "Patient-customer-hidden", 
   "owner": "Administrator", 
   "parent": null, 
   "parentfield": null, 
   "parenttype": null, 
   "property": "hidden", 
   "property_type": "Check", 
   "value": "1"
  }, 
  {
   "_assign": null, 
   "_comments": null, 
   "_liked_by": null, 
   "_user_tags": null, 
   "creation": "2019-06-03 19:19:21.658565", 
   "default_value": null, 
   "doc_type": "Patient", 
   "docstatus": 0, 
   "doctype_or_field": "DocField", 
   "field_name": "naming_series", 
   "idx": 0, 
   "modified": "2019-06-10 15:49:03.400563", 
   "modified_by": "Administrator", 
   "name": "Patient-naming_series-options", 
   "owner": "Administrator", 
   "parent": null, 
   "parentfield": null, 
   "parenttype": null, 
   "property": "options", 
   "property_type": "Text", 
   "value": "PP.####\nP.YY.MM.####\nP.####"
  }
 ], 
 "sync_on_migrate": 1
}