{
 "custom_fields": [
  {
   "_assign": null, 
   "_comments": null, 
   "_liked_by": null, 
   "_user_tags": null, 
   "allow_on_submit": 0, 
   "bold": 0, 
   "collapsible": 0, 
   "collapsible_depends_on": null, 
   "columns": 0, 
   "creation": "2019-07-22 15:08:56.281364", 
   "default": null, 
   "depends_on": null, 
   "description": null, 
   "docstatus": 0, 
   "dt": "Patient", 
   "fetch_from": null, 
   "fetch_if_empty": 0, 
   "fieldname": "lead_name", 
   "fieldtype": "Data", 
   "hidden": 1, 
   "idx": 4, 
   "ignore_user_permissions": 0, 
   "ignore_xss_filter": 0, 
   "in_global_search": 0, 
   "in_list_view": 0, 
   "in_standard_filter": 0, 
   "insert_after": "naming_series", 
   "label": "Lead Name", 
   "modified": "2019-07-22 15:08:56.281364", 
   "modified_by": "Administrator", 
   "name": "Patient-lead_name", 
   "no_copy": 0, 
   "options": "Lead", 
   "owner": "Administrator", 
   "parent": null, 
   "parentfield": null, 
   "parenttype": null, 
   "permlevel": 0, 
   "precision": "", 
   "print_hide": 0, 
   "print_hide_if_no_value": 0, 
   "print_width": null, 
   "read_only": 1, 
   "report_hide": 0, 
   "reqd": 0, 
   "search_index": 0, 
   "translatable": 1, 
   "unique": 0, 
   "width": null
  }, 
  {
   "_assign": null, 
   "_comments": null, 
   "_liked_by": null, 
   "_user_tags": null, 
   "allow_on_submit": 0, 
   "bold": 0, 
   "collapsible": 0, 
   "collapsible_depends_on": null, 
   "columns": 0, 
   "creation": "2019-07-17 12:21:24.266833", 
   "default": "India", 
   "depends_on": null, 
   "description": null, 
   "docstatus": 0, 
   "dt": "Patient", 
   "fetch_from": null, 
   "fetch_if_empty": 0, 
   "fieldname": "country", 
   "fieldtype": "Link", 
   "hidden": 0, 
   "idx": 32, 
   "ignore_user_permissions": 0, 
   "ignore_xss_filter": 0, 
   "in_global_search": 0, 
   "in_list_view": 0, 
   "in_standard_filter": 0, 
   "insert_after": "state", 
   "label": "Country", 
   "modified": "2019-07-17 12:21:24.266833", 
   "modified_by": "Administrator", 
   "name": "Patient-country", 
   "no_copy": 0, 
   "options": "Country", 
   "owner": "Administrator", 
   "parent": null, 
   "parentfield": null, 
   "parenttype": null, 
   "permlevel": 0, 
   "precision": "", 
   "print_hide": 0, 
   "print_hide_if_no_value": 0, 
   "print_width": null, 
   "read_only": 0, 
   "report_hide": 0, 
   "reqd": 0, 
   "search_index": 0, 
   "translatable": 0, 
   "unique": 0, 
   "width": null
  }, 
  {
   "_assign": null, 
   "_comments": null, 
   "_liked_by": null, 
   "_user_tags": null, 
   "allow_on_submit": 0, 
   "bold": 0, 
   "collapsible": 0, 
   "collapsible_depends_on": null, 
   "columns": 0, 
   "creation": "2019-07-17 12:17:22.321898", 
   "default": null, 
   "depends_on": null, 
   "description": null, 
   "docstatus": 0, 
   "dt": "Patient", 
   "fetch_from": null, 
   "fetch_if_empty": 0, 
   "fieldname": "address_name", 
   "fieldtype": "Link", 
   "hidden": 1, 
   "idx": 33, 
   "ignore_user_permissions": 0, 
   "ignore_xss_filter": 0, 
   "in_global_search": 0, 
   "in_list_view": 0, 
   "in_standard_filter": 0, 
   "insert_after": "country", 
   "label": "Address Name", 
   "modified": "2019-07-17 12:17:22.321898", 
   "modified_by": "Administrator", 
   "name": "Patient-address_name", 
   "no_copy": 0, 
   "options": "Address", 
   "owner": "Administrator", 
   "parent": null, 
   "parentfield": null, 
   "parenttype": null, 
   "permlevel": 0, 
   "precision": "", 
   "print_hide": 0, 
   "print_hide_if_no_value": 0, 
   "print_width": null, 
   "read_only": 0, 
   "report_hide": 0, 
   "reqd": 0, 
   "search_index": 0, 
   "translatable": 0, 
   "unique": 0, 
   "width": null
  }, 
  {
   "_assign": null, 
   "_comments": null, 
   "_liked_by": null, 
   "_user_tags": null, 
   "allow_on_submit": 0, 
   "bold": 1, 
   "collapsible": 0, 
   "collapsible_depends_on": null, 
   "columns": 0, 
   "creation": "2019-07-15 12:29:05.266761", 
   "default": null, 
   "depends_on": null, 
   "description": null, 
   "docstatus": 0, 
   "dt": "Patient", 
   "fetch_from": null, 
   "fetch_if_empty": 0, 
   "fieldname": "state", 
   "fieldtype": "Data", 
   "hidden": 0, 
   "idx": 31, 
   "ignore_user_permissions": 0, 
   "ignore_xss_filter": 0, 
   "in_global_search": 0, 
   "in_list_view": 0, 
   "in_standard_filter": 0, 
   "insert_after": "city", 
   "label": "State", 
   "modified": "2019-07-15 12:29:05.266761", 
   "modified_by": "Administrator", 
   "name": "Patient-state", 
   "no_copy": 0, 
   "options": null, 
   "owner": "Administrator", 
   "parent": null, 
   "parentfield": null, 
   "parenttype": null, 
   "permlevel": 0, 
   "precision": "", 
   "print_hide": 0, 
   "print_hide_if_no_value": 0, 
   "print_width": null, 
   "read_only": 0, 
   "report_hide": 0, 
   "reqd": 0, 
   "search_index": 0, 
   "translatable": 1, 
   "unique": 0, 
   "width": null
  }, 
  {
   "_assign": null, 
   "_comments": null, 
   "_liked_by": null, 
   "_user_tags": null, 
   "allow_on_submit": 0, 
   "bold": 1, 
   "collapsible": 0, 
   "collapsible_depends_on": null, 
   "columns": 0, 
   "creation": "2019-07-15 12:29:03.819381", 
   "default": null, 
   "depends_on": null, 
   "description": null, 
   "docstatus": 0, 
   "dt": "Patient", 
   "fetch_from": null, 
   "fetch_if_empty": 0, 
   "fieldname": "city", 
   "fieldtype": "Data", 
   "hidden": 0, 
   "idx": 30, 
   "ignore_user_permissions": 0, 
   "ignore_xss_filter": 0, 
   "in_global_search": 0, 
   "in_list_view": 0, 
   "in_standard_filter": 0, 
   "insert_after": "column_break_27", 
   "label": "City", 
   "modified": "2019-07-15 12:29:03.819381", 
   "modified_by": "Administrator", 
   "name": "Patient-city", 
   "no_copy": 0, 
   "options": null, 
   "owner": "Administrator", 
   "parent": null, 
   "parentfield": null, 
   "parenttype": null, 
   "permlevel": 0, 
   "precision": "", 
   "print_hide": 0, 
   "print_hide_if_no_value": 0, 
   "print_width": null, 
   "read_only": 0, 
   "report_hide": 0, 
   "reqd": 0, 
   "search_index": 0, 
   "translatable": 1, 
   "unique": 0, 
   "width": null
  }, 
  {
   "_assign": null, 
   "_comments": null, 
   "_liked_by": null, 
   "_user_tags": null, 
   "allow_on_submit": 0, 
   "bold": 1, 
   "collapsible": 0, 
   "collapsible_depends_on": null, 
   "columns": 0, 
   "creation": "2019-07-15 12:29:03.276050", 
   "default": null, 
   "depends_on": null, 
   "description": null, 
   "docstatus": 0, 
   "dt": "Patient", 
   "fetch_from": null, 
   "fetch_if_empty": 0, 
   "fieldname": "column_break_27", 
   "fieldtype": "Column Break", 
   "hidden": 0, 
   "idx": 29, 
   "ignore_user_permissions": 0, 
   "ignore_xss_filter": 0, 
   "in_global_search": 0, 
   "in_list_view": 0, 
   "in_standard_filter": 0, 
   "insert_after": "zip_code", 
   "label": null, 
   "modified": "2019-07-15 12:29:03.276050", 
   "modified_by": "Administrator", 
   "name": "Patient-column_break_27", 
   "no_copy": 0, 
   "options": null, 
   "owner": "Administrator", 
   "parent": null, 
   "parentfield": null, 
   "parenttype": null, 
   "permlevel": 0, 
   "precision": "", 
   "print_hide": 0, 
   "print_hide_if_no_value": 0, 
   "print_width": null, 
   "read_only": 0, 
   "report_hide": 0, 
   "reqd": 0, 
   "search_index": 0, 
   "translatable": 0, 
   "unique": 0, 
   "width": null
  }, 
  {
   "_assign": null, 
   "_comments": null, 
   "_liked_by": null, 
   "_user_tags": null, 
   "allow_on_submit": 0, 
   "bold": 1, 
   "collapsible": 0, 
   "collapsible_depends_on": null, 
   "columns": 0, 
   "creation": "2019-07-15 12:29:01.780445", 
   "default": null, 
   "depends_on": null, 
   "description": null, 
   "docstatus": 0, 
   "dt": "Patient", 
   "fetch_from": null, 
   "fetch_if_empty": 0, 
   "fieldname": "zip_code", 
   "fieldtype": "Data", 
   "hidden": 0, 
   "idx": 28, 
   "ignore_user_permissions": 0, 
   "ignore_xss_filter": 0, 
   "in_global_search": 0, 
   "in_list_view": 0, 
   "in_standard_filter": 0, 
   "insert_after": "address_line2", 
   "label": "Zip Code", 
   "modified": "2019-07-15 12:29:01.780445", 
   "modified_by": "Administrator", 
   "name": "Patient-zip_code", 
   "no_copy": 0, 
   "options": null, 
   "owner": "Administrator", 
   "parent": null, 
   "parentfield": null, 
   "parenttype": null, 
   "permlevel": 0, 
   "precision": "", 
   "print_hide": 0, 
   "print_hide_if_no_value": 0, 
   "print_width": null, 
   "read_only": 0, 
   "report_hide": 0, 
   "reqd": 0, 
   "search_index": 0, 
   "translatable": 1, 
   "unique": 0, 
   "width": null
  }, 
  {
   "_assign": null, 
   "_comments": null, 
   "_liked_by": null, 
   "_user_tags": null, 
   "allow_on_submit": 0, 
   "bold": 1, 
   "collapsible": 0, 
   "collapsible_depends_on": null, 
   "columns": 0, 
   "creation": "2019-07-15 12:28:59.279311", 
   "default": null, 
   "depends_on": null, 
   "description": null, 
   "docstatus": 0, 
   "dt": "Patient", 
   "fetch_from": null, 
   "fetch_if_empty": 0, 
   "fieldname": "address_line2", 
   "fieldtype": "Data", 
   "hidden": 0, 
   "idx": 27, 
   "ignore_user_permissions": 0, 
   "ignore_xss_filter": 0, 
   "in_global_search": 0, 
   "in_list_view": 0, 
   "in_standard_filter": 0, 
   "insert_after": "address_line1", 
   "label": "Address Line2", 
   "modified": "2019-07-15 12:28:59.279311", 
   "modified_by": "Administrator", 
   "name": "Patient-address_line2", 
   "no_copy": 0, 
   "options": null, 
   "owner": "Administrator", 
   "parent": null, 
   "parentfield": null, 
   "parenttype": null, 
   "permlevel": 0, 
   "precision": "", 
   "print_hide": 0, 
   "print_hide_if_no_value": 0, 
   "print_width": null, 
   "read_only": 0, 
   "report_hide": 0, 
   "reqd": 0, 
   "search_index": 0, 
   "translatable": 1, 
   "unique": 0, 
   "width": null
  }, 
  {
   "_assign": null, 
   "_comments": null, 
   "_liked_by": null, 
   "_user_tags": null, 
   "allow_on_submit": 0, 
   "bold": 1, 
   "collapsible": 0, 
   "collapsible_depends_on": null, 
   "columns": 0, 
   "creation": "2019-07-15 12:28:57.246749", 
   "default": null, 
   "depends_on": null, 
   "description": null, 
   "docstatus": 0, 
   "dt": "Patient", 
   "fetch_from": null, 
   "fetch_if_empty": 0, 
   "fieldname": "address_line1", 
   "fieldtype": "Data", 
   "hidden": 0, 
   "idx": 26, 
   "ignore_user_permissions": 0, 
   "ignore_xss_filter": 0, 
   "in_global_search": 0, 
   "in_list_view": 0, 
   "in_standard_filter": 0, 
   "insert_after": "address_detail", 
   "label": "Address Line 1", 
   "modified": "2019-07-15 12:28:57.246749", 
   "modified_by": "Administrator", 
   "name": "Patient-address_line1", 
   "no_copy": 0, 
   "options": null, 
   "owner": "Administrator", 
   "parent": null, 
   "parentfield": null, 
   "parenttype": null, 
   "permlevel": 0, 
   "precision": "", 
   "print_hide": 0, 
   "print_hide_if_no_value": 0, 
   "print_width": null, 
   "read_only": 0, 
   "report_hide": 0, 
   "reqd": 0, 
   "search_index": 0, 
   "translatable": 1, 
   "unique": 0, 
   "width": null
  }, 
  {
   "_assign": null, 
   "_comments": null, 
   "_liked_by": null, 
   "_user_tags": null, 
   "allow_on_submit": 0, 
   "bold": 1, 
   "collapsible": 1, 
   "collapsible_depends_on": null, 
   "columns": 0, 
   "creation": "2019-07-15 12:28:56.352995", 
   "default": null, 
   "depends_on": null, 
   "description": null, 
   "docstatus": 0, 
   "dt": "Patient", 
   "fetch_from": null, 
   "fetch_if_empty": 0, 
   "fieldname": "address_detail", 
   "fieldtype": "Section Break", 
   "hidden": 0, 
   "idx": 25, 
   "ignore_user_permissions": 0, 
   "ignore_xss_filter": 0, 
   "in_global_search": 0, 
   "in_list_view": 0, 
   "in_standard_filter": 0, 
   "insert_after": "patient_relation", 
   "label": "Address Detail", 
   "modified": "2019-07-15 12:28:56.352995", 
   "modified_by": "Administrator", 
   "name": "Patient-address_detail", 
   "no_copy": 0, 
   "options": null, 
   "owner": "Administrator", 
   "parent": null, 
   "parentfield": null, 
   "parenttype": null, 
   "permlevel": 0, 
   "precision": "", 
   "print_hide": 0, 
   "print_hide_if_no_value": 0, 
   "print_width": null, 
   "read_only": 0, 
   "report_hide": 0, 
   "reqd": 0, 
   "search_index": 0, 
   "translatable": 0, 
   "unique": 0, 
   "width": null
  }, 
  {
   "_assign": null, 
   "_comments": null, 
   "_liked_by": null, 
   "_user_tags": null, 
   "allow_on_submit": 0, 
   "bold": 0, 
   "collapsible": 0, 
   "collapsible_depends_on": null, 
   "columns": 0, 
   "creation": "2019-06-12 10:15:01.568552", 
   "default": null, 
   "depends_on": null, 
   "description": null, 
   "docstatus": 0, 
   "dt": "Patient", 
   "fetch_from": null, 
   "fetch_if_empty": 0, 
   "fieldname": "referrer_phone_no", 
   "fieldtype": "Data", 
   "hidden": 0, 
   "idx": 21, 
   "ignore_user_permissions": 0, 
   "ignore_xss_filter": 0, 
   "in_global_search": 0, 
   "in_list_view": 0, 
   "in_standard_filter": 0, 
   "insert_after": "referrer_name", 
   "label": "Referrer Phone No", 
   "modified": "2019-06-12 10:15:01.568552", 
   "modified_by": "Administrator", 
   "name": "Patient-referrer_phone_no", 
   "no_copy": 0, 
   "options": null, 
   "owner": "Administrator", 
   "parent": null, 
   "parentfield": null, 
   "parenttype": null, 
   "permlevel": 0, 
   "precision": "", 
   "print_hide": 0, 
   "print_hide_if_no_value": 0, 
   "print_width": null, 
   "read_only": 0, 
   "report_hide": 0, 
   "reqd": 0, 
   "search_index": 0, 
   "translatable": 1, 
   "unique": 0, 
   "width": null
  }, 
  {
   "_assign": null, 
   "_comments": null, 
   "_liked_by": null, 
   "_user_tags": null, 
   "allow_on_submit": 0, 
   "bold": 0, 
   "collapsible": 0, 
   "collapsible_depends_on": null, 
   "columns": 0, 
   "creation": "2019-06-12 10:15:00.947530", 
   "default": null, 
   "depends_on": null, 
   "description": null, 
   "docstatus": 0, 
   "dt": "Patient", 
   "fetch_from": null, 
   "fetch_if_empty": 0, 
   "fieldname": "referrer_name", 
   "fieldtype": "Data", 
   "hidden": 0, 
   "idx": 20, 
   "ignore_user_permissions": 0, 
   "ignore_xss_filter": 0, 
   "in_global_search": 0, 
   "in_list_view": 0, 
   "in_standard_filter": 0, 
   "insert_after": "phone", 
   "label": "Referrer Name", 
   "modified": "2019-06-12 10:15:00.947530", 
   "modified_by": "Administrator", 
   "name": "Patient-referrer_name", 
   "no_copy": 0, 
   "options": null, 
   "owner": "Administrator", 
   "parent": null, 
   "parentfield": null, 
   "parenttype": null, 
   "permlevel": 0, 
   "precision": "", 
   "print_hide": 0, 
   "print_hide_if_no_value": 0, 
   "print_width": null, 
   "read_only": 0, 
   "report_hide": 0, 
   "reqd": 0, 
   "search_index": 0, 
   "translatable": 1, 
   "unique": 0, 
   "width": null
  }, 
  {
   "_assign": null, 
   "_comments": null, 
   "_liked_by": null, 
   "_user_tags": null, 
   "allow_on_submit": 0, 
   "bold": 0, 
   "collapsible": 0, 
   "collapsible_depends_on": null, 
   "columns": 0, 
   "creation": "2019-06-11 15:25:44.429079", 
   "default": null, 
   "depends_on": null, 
   "description": null, 
   "docstatus": 0, 
   "dt": "Patient", 
   "fetch_from": null, 
   "fetch_if_empty": 0, 
   "fieldname": "family_name", 
   "fieldtype": "Link", 
   "hidden": 0, 
   "idx": 13, 
   "ignore_user_permissions": 0, 
   "ignore_xss_filter": 0, 
   "in_global_search": 0, 
   "in_list_view": 0, 
   "in_standard_filter": 0, 
   "insert_after": "image", 
   "label": "Family Name", 
   "modified": "2019-06-01 11:12:46.009241", 
   "modified_by": "Administrator", 
   "name": "Patient-family_name", 
   "no_copy": 0, 
   "options": "Family", 
   "owner": "Administrator", 
   "parent": null, 
   "parentfield": null, 
   "parenttype": null, 
   "permlevel": 0, 
   "precision": "", 
   "print_hide": 0, 
   "print_hide_if_no_value": 0, 
   "print_width": null, 
   "read_only": 0, 
   "report_hide": 0, 
   "reqd": 0, 
   "search_index": 0, 
   "translatable": 0, 
   "unique": 0, 
   "width": null
  }
 ], 
 "custom_perms": [
  {
   "_assign": null, 
   "_comments": null, 
   "_liked_by": null, 
   "_user_tags": null, 
   "amend": 0, 
   "cancel": 0, 
   "create": 1, 
   "creation": "2017-01-23 14:03:49.084370", 
   "delete": 0, 
   "docstatus": 0, 
   "email": 1, 
   "export": 1, 
   "idx": 2, 
   "if_owner": 0, 
   "import": 0, 
   "modified": "2019-06-05 14:14:14.277125", 
   "modified_by": "Administrator", 
   "name": "430447308a", 
   "owner": "Administrator", 
   "parent": "Patient", 
   "parentfield": "permissions", 
   "parenttype": "DocType", 
   "permlevel": 0, 
   "print": 1, 
   "read": 1, 
   "report": 1, 
   "role": "Laboratory User", 
   "set_user_permissions": 0, 
   "share": 1, 
   "submit": 0, 
   "write": 1
  }, 
  {
   "_assign": null, 
   "_comments": null, 
   "_liked_by": null, 
   "_user_tags": null, 
   "amend": 0, 
   "cancel": 0, 
   "create": 1, 
   "creation": "2017-01-23 14:03:49.084370", 
   "delete": 0, 
   "docstatus": 0, 
   "email": 1, 
   "export": 1, 
   "idx": 3, 
   "if_owner": 0, 
   "import": 0, 
   "modified": "2019-06-05 14:14:14.296371", 
   "modified_by": "Administrator", 
   "name": "af8b6ffb9a", 
   "owner": "Administrator", 
   "parent": "Patient", 
   "parentfield": "permissions", 
   "parenttype": "DocType", 
   "permlevel": 0, 
   "print": 1, 
   "read": 1, 
   "report": 1, 
   "role": "Nursing User", 
   "set_user_permissions": 0, 
   "share": 1, 
   "submit": 0, 
   "write": 1
  }, 
  {
   "_assign": null, 
   "_comments": null, 
   "_liked_by": null, 
   "_user_tags": null, 
   "amend": 0, 
   "cancel": 0, 
   "create": 1, 
   "creation": "2017-01-23 14:03:49.084370", 
   "delete": 0, 
   "docstatus": 0, 
   "email": 1, 
   "export": 1, 
   "idx": 1, 
   "if_owner": 0, 
   "import": 0, 
   "modified": "2019-06-05 14:14:14.305504", 
   "modified_by": "Administrator", 
   "name": "9fef0f32db", 
   "owner": "Administrator", 
   "parent": "Patient", 
   "parentfield": "permissions", 
   "parenttype": "DocType", 
   "permlevel": 0, 
   "print": 1, 
   "read": 1, 
   "report": 0, 
   "role": "Physician", 
   "set_user_permissions": 0, 
   "share": 1, 
   "submit": 0, 
   "write": 1
  }, 
  {
   "_assign": null, 
   "_comments": null, 
   "_liked_by": null, 
   "_user_tags": null, 
   "amend": 0, 
   "cancel": 0, 
   "create": 1, 
   "creation": "2019-06-05 15:27:37.292585", 
   "delete": 0, 
   "docstatus": 0, 
   "email": 0, 
   "export": 0, 
   "idx": 0, 
   "if_owner": 0, 
   "import": 0, 
   "modified": "2019-06-05 15:27:37.292585", 
   "modified_by": "Administrator", 
   "name": "5463fc470a", 
   "owner": "Administrator", 
   "parent": "Patient", 
   "parentfield": "permissions", 
   "parenttype": "DocType", 
   "permlevel": 0, 
   "print": 0, 
   "read": 1, 
   "report": 0, 
   "role": "Oralcare Receptionist", 
   "set_user_permissions": 0, 
   "share": 0, 
   "submit": 0, 
   "write": 1
  }, 
  {
   "_assign": null, 
   "_comments": null, 
   "_liked_by": null, 
   "_user_tags": null, 
   "amend": 0, 
   "cancel": 0, 
   "create": 0, 
   "creation": "2019-06-26 14:03:59.927927", 
   "delete": 1, 
   "docstatus": 0, 
   "email": 0, 
   "export": 1, 
   "idx": 0, 
   "if_owner": 0, 
   "import": 0, 
   "modified": "2019-06-26 14:03:59.927927", 
   "modified_by": "Administrator", 
   "name": "fb6dfb9d9d", 
   "owner": "Administrator", 
   "parent": "Patient", 
   "parentfield": "permissions", 
   "parenttype": "DocType", 
   "permlevel": 0, 
   "print": 0, 
   "read": 1, 
   "report": 0, 
   "role": "Doctor", 
   "set_user_permissions": 0, 
   "share": 0, 
   "submit": 0, 
   "write": 0
  }, 
  {
   "_assign": null, 
   "_comments": null, 
   "_liked_by": null, 
   "_user_tags": null, 
   "amend": 0, 
   "cancel": 0, 
   "create": 0, 
   "creation": "2019-06-26 15:14:18.706783", 
   "delete": 0, 
   "docstatus": 0, 
   "email": 0, 
   "export": 1, 
   "idx": 0, 
   "if_owner": 0, 
   "import": 0, 
   "modified": "2019-06-26 15:14:18.706783", 
   "modified_by": "Administrator", 
   "name": "f1b97dad3f", 
   "owner": "Administrator", 
   "parent": "Patient", 
   "parentfield": "permissions", 
   "parenttype": "DocType", 
   "permlevel": 0, 
   "print": 0, 
   "read": 1, 
   "report": 0, 
   "role": "IT", 
   "set_user_permissions": 0, 
   "share": 0, 
   "submit": 0, 
   "write": 0
  }
 ], 
 "doctype": "Patient", 
 "property_setters": [
  {
   "_assign": null, 
   "_comments": null, 
   "_liked_by": null, 
   "_user_tags": null, 
   "creation": "2019-06-03 19:19:21.658565", 
   "default_value": null, 
   "doc_type": "Patient", 
   "docstatus": 0, 
   "doctype_or_field": "DocField", 
   "field_name": "naming_series", 
   "idx": 0, 
   "modified": "2019-07-26 09:24:06.255142", 
   "modified_by": "Administrator", 
   "name": "Patient-naming_series-options", 
   "owner": "Administrator", 
   "parent": null, 
   "parentfield": null, 
   "parenttype": null, 
   "property": "options", 
   "property_type": "Text", 
   "value": "P.YY.MM.####"
  }, 
  {
   "_assign": null, 
   "_comments": null, 
   "_liked_by": null, 
   "_user_tags": null, 
   "creation": "2019-07-26 09:24:06.229527", 
   "default_value": null, 
   "doc_type": "Patient", 
   "docstatus": 0, 
   "doctype_or_field": "DocField", 
   "field_name": "naming_series", 
   "idx": 0, 
   "modified": "2019-07-26 09:24:06.229527", 
   "modified_by": "Administrator", 
   "name": "Patient-naming_series-default", 
   "owner": "Administrator", 
   "parent": null, 
   "parentfield": null, 
   "parenttype": null, 
   "property": "default", 
   "property_type": "Text", 
   "value": "P.YY.MM.####"
  }, 
  {
   "_assign": null, 
   "_comments": null, 
   "_liked_by": null, 
   "_user_tags": null, 
   "creation": "2019-07-22 15:08:56.172908", 
   "default_value": null, 
   "doc_type": "Patient", 
   "docstatus": 0, 
   "doctype_or_field": "DocType", 
   "field_name": null, 
   "idx": 0, 
   "modified": "2019-07-22 15:08:56.172908", 
   "modified_by": "Administrator", 
   "name": "Patient-read_only_onload", 
   "owner": "Administrator", 
   "parent": null, 
   "parentfield": null, 
   "parenttype": null, 
   "property": "read_only_onload", 
   "property_type": "Check", 
   "value": null
  }, 
  {
   "_assign": null, 
   "_comments": null, 
   "_liked_by": null, 
   "_user_tags": null, 
   "creation": "2019-07-15 02:44:55.032334", 
   "default_value": null, 
   "doc_type": "Patient", 
   "docstatus": 0, 
   "doctype_or_field": "DocField", 
   "field_name": "phone", 
   "idx": 0, 
   "modified": "2019-07-15 02:44:55.032334", 
   "modified_by": "Administrator", 
   "name": "Patient-phone-label", 
   "owner": "Administrator", 
   "parent": null, 
   "parentfield": null, 
   "parenttype": null, 
   "property": "label", 
   "property_type": "Data", 
   "value": "Alternate Mobile"
  }, 
  {
   "_assign": null, 
   "_comments": null, 
   "_liked_by": null, 
   "_user_tags": null, 
   "creation": "2019-06-11 17:14:02.430219", 
   "default_value": null, 
   "doc_type": "Patient", 
   "docstatus": 0, 
   "doctype_or_field": "DocField", 
   "field_name": "blood_group", 
   "idx": 0, 
   "modified": "2019-06-11 17:14:02.430219", 
   "modified_by": "Administrator", 
   "name": "Patient-blood_group-label", 
   "owner": "Administrator", 
   "parent": null, 
   "parentfield": null, 
   "parenttype": null, 
   "property": "idx", 
   "property_type": "Int", 
   "value": "1"
  }, 
  {
   "_assign": null, 
   "_comments": null, 
   "_liked_by": null, 
   "_user_tags": null, 
   "creation": "2019-06-11 12:57:19.191169", 
   "default_value": null, 
   "doc_type": "Patient", 
   "docstatus": 0, 
   "doctype_or_field": "DocField", 
   "field_name": "blood_group", 
   "idx": 0, 
   "modified": "2019-06-11 12:57:19.191169", 
   "modified_by": "Administrator", 
   "name": "Patient-blood_group-options", 
   "owner": "Administrator", 
   "parent": null, 
   "parentfield": null, 
   "parenttype": null, 
   "property": "options", 
   "property_type": "Text", 
   "value": "\nA Positive\nA Negative\nAB Positive\nAB Negative\nB Positive\nB Negative\nO Positive\nO Negative\nBombay"
  }, 
  {
   "_assign": null, 
   "_comments": null, 
   "_liked_by": null, 
   "_user_tags": null, 
   "creation": "2019-06-11 12:56:40.490420", 
   "default_value": null, 
   "doc_type": "Patient", 
   "docstatus": 0, 
   "doctype_or_field": "DocField", 
   "field_name": "report_preference", 
   "idx": 0, 
   "modified": "2019-06-11 12:56:40.490420", 
   "modified_by": "Administrator", 
   "name": "Patient-report_preference-default", 
   "owner": "Administrator", 
   "parent": null, 
   "parentfield": null, 
   "parenttype": null, 
   "property": "default", 
   "property_type": "Text", 
   "value": "Email"
  }, 
  {
   "_assign": null, 
   "_comments": null, 
   "_liked_by": null, 
   "_user_tags": null, 
   "creation": "2019-06-11 12:56:40.480727", 
   "default_value": null, 
   "doc_type": "Patient", 
   "docstatus": 0, 
   "doctype_or_field": "DocField", 
   "field_name": "customer", 
   "idx": 0, 
   "modified": "2019-06-11 12:56:40.480727", 
   "modified_by": "Administrator", 
   "name": "Patient-customer-hidden", 
   "owner": "Administrator", 
   "parent": null, 
   "parentfield": null, 
   "parenttype": null, 
   "property": "hidden", 
   "property_type": "Check", 
   "value": "1"
  }
 ], 
 "sync_on_migrate": 1
}